numwords_to_nums/__init__.py
numwords_to_nums/constants.py
numwords_to_nums/numwords_to_nums.py
numwords_to_nums/rules.py
numwords_to_nums/text_processing_helpers.py
numwords_to_nums/tokens_basic.py
numwords_to_nums/tokens_rules.py
numwords_to_nums-1.2.0.dist-info/LICENSE.md
numwords_to_nums-1.2.0.dist-info/METADATA
numwords_to_nums-1.2.0.dist-info/WHEEL
numwords_to_nums-1.2.0.dist-info/top_level.txt
numwords_to_nums-1.2.0.dist-info/RECORD
