Metadata-Version: 2.1
Name: numwords-to-nums
Version: 1.2.0
Summary: Python library for converting numerical words (textual numbers) to numbers
Author: Sarthak, Arpit
Author-email: Sarthak <sarthak6jan16@gmail.com>, Arpit <joshia296@gmail.com>
Keywords: text2numbers,words2numbers,digits,numbers,ordinal numbers,converter,text to digits,words to numbers
Classifier: License :: OSI Approved :: MIT License
Classifier: Programming Language :: Python
Classifier: Programming Language :: Python :: 3
License-File: LICENSE.md
